{"ship":"gu97","width":1051,"height":501,"bands":[{"id":1,"points":[{"x":12.45,"y":-2.89},{"x":96.97,"y":-2.89},{"x":96.97,"y":60.94},{"x":96.77,"y":63.86},{"x":96.57,"y":65.94},{"x":96.17,"y":69.28},{"x":95.78,"y":71.78},{"x":92.59,"y":83.05},{"x":60.38,"y":101.4},{"x":48.84,"y":101.4},{"x":16.83,"y":83.05},{"x":13.65,"y":71.78},{"x":13.05,"y":68.03},{"x":12.85,"y":66.36},{"x":12.65,"y":64.27},{"x":12.45,"y":61.77}]},{"id":2,"points":[{"x":10.84,"y":-5.46},{"x":98.59,"y":-5.46},{"x":98.59,"y":60.81},{"x":98.38,"y":63.84},{"x":98.17,"y":66.01},{"x":97.76,"y":69.48},{"x":97.35,"y":72.07},{"x":94.04,"y":83.77},{"x":60.6,"y":102.83},{"x":48.62,"y":102.83},{"x":15.38,"y":83.77},{"x":12.08,"y":72.07},{"x":11.46,"y":68.18},{"x":11.25,"y":66.44},{"x":11.04,"y":64.28},{"x":10.84,"y":61.68}]},{"id":3,"points":[{"x":9.22,"y":-8.02},{"x":100.21,"y":-8.02},{"x":100.21,"y":60.69},{"x":99.99,"y":63.83},{"x":99.78,"y":66.08},{"x":99.35,"y":69.67},{"x":98.92,"y":72.36},{"x":95.5,"y":84.49},{"x":60.81,"y":104.25},{"x":48.4,"y":104.25},{"x":13.93,"y":84.49},{"x":10.5,"y":72.36},{"x":9.86,"y":68.32},{"x":9.65,"y":66.53},{"x":9.43,"y":64.28},{"x":9.22,"y":61.59}]}]}
