{"ship":"python","width":823,"height":674,"bands":[{"id":1,"points":[{"x":20.82,"y":22.05},{"x":21.07,"y":20.19},{"x":23.1,"y":6.55},{"x":23.36,"y":5},{"x":23.61,"y":4.07},{"x":26.91,"y":-1.82},{"x":81.26,"y":-1.82},{"x":84.81,"y":4.38},{"x":85.07,"y":5.93},{"x":87.35,"y":21.43},{"x":87.35,"y":23.6},{"x":67.29,"y":80.66},{"x":66.28,"y":83.45},{"x":56.37,"y":102.06},{"x":56.12,"y":102.37},{"x":52.05,"y":102.37},{"x":41.9,"y":83.14},{"x":41.64,"y":82.52},{"x":20.82,"y":23.6}]},{"id":2,"points":[{"x":19.67,"y":21.35},{"x":19.93,"y":19.42},{"x":22.04,"y":5.25},{"x":22.3,"y":3.64},{"x":22.57,"y":2.67},{"x":26,"y":-3.44},{"x":82.42,"y":-3.44},{"x":86.11,"y":3},{"x":86.38,"y":4.61},{"x":88.75,"y":20.7},{"x":88.75,"y":22.96},{"x":67.92,"y":82.2},{"x":66.86,"y":85.1},{"x":56.58,"y":104.41},{"x":56.32,"y":104.73},{"x":52.1,"y":104.73},{"x":41.55,"y":84.77},{"x":41.29,"y":84.13},{"x":19.67,"y":22.96}]},{"id":3,"points":[{"x":18.52,"y":20.64},{"x":18.79,"y":18.64},{"x":20.98,"y":3.95},{"x":21.25,"y":2.28},{"x":21.52,"y":1.28},{"x":25.08,"y":-5.06},{"x":83.58,"y":-5.06},{"x":87.41,"y":1.61},{"x":87.68,"y":3.28},{"x":90.14,"y":19.97},{"x":90.14,"y":22.31},{"x":68.55,"y":83.73},{"x":67.45,"y":86.74},{"x":56.79,"y":106.77},{"x":56.52,"y":107.1},{"x":52.14,"y":107.1},{"x":41.21,"y":86.4},{"x":40.93,"y":85.74},{"x":18.52,"y":22.31}]}]}
