{"ship":"viper-mk-3","width":962,"height":632,"bands":[{"id":1,"points":[{"x":29.01,"y":12.95},{"x":29.44,"y":-2.59},{"x":91.14,"y":-2.59},{"x":91.36,"y":12.62},{"x":91.36,"y":13.61},{"x":70.94,"y":88.35},{"x":67.46,"y":96.29},{"x":67.24,"y":96.62},{"x":62.46,"y":101.58},{"x":62.25,"y":101.58},{"x":53.12,"y":96.62},{"x":49.86,"y":89.34},{"x":49.43,"y":88.02},{"x":29.01,"y":13.61}]},{"id":2,"points":[{"x":27.81,"y":11.24},{"x":28.26,"y":-4.89},{"x":92.32,"y":-4.89},{"x":92.55,"y":10.9},{"x":92.55,"y":11.93},{"x":71.34,"y":89.53},{"x":67.73,"y":97.77},{"x":67.51,"y":98.11},{"x":62.55,"y":103.26},{"x":62.32,"y":103.26},{"x":52.85,"y":98.11},{"x":49.46,"y":90.56},{"x":49.01,"y":89.19},{"x":27.81,"y":11.93}]},{"id":3,"points":[{"x":26.61,"y":9.54},{"x":27.08,"y":-7.2},{"x":93.5,"y":-7.2},{"x":93.74,"y":9.18},{"x":93.74,"y":10.25},{"x":71.75,"y":90.71},{"x":68.01,"y":99.25},{"x":67.78,"y":99.61},{"x":62.63,"y":104.95},{"x":62.4,"y":104.95},{"x":52.57,"y":99.61},{"x":49.06,"y":91.77},{"x":48.6,"y":90.35},{"x":26.61,"y":10.25}]}]}
